{
    "Ar36": {
        "error": 0.0008637810987471119,
        "error_type": "SEM",
        "filter_outliers_dict": {
            "filter_outliers": true,
            "iterations": 1,
            "std_devs": 3,
            "use_iqr_filtering": false,
            "use_standard_deviation_filtering": false
        },
        "fit": "Parabolic",
        "fn": 339,
        "include_baseline_error": false,
        "n": 340,
        "outlier_excluded": [
            39
        ],
        "reviewed": true,
        "user_excluded": [],
        "value": 0.09599126357194707
    },
    "Ar37": {
        "error": 0.018045888534041172,
        "error_type": "SEM",
        "filter_outliers_dict": {
            "filter_outliers": true,
            "iterations": 1,
            "std_devs": 3,
            "use_iqr_filtering": false,
            "use_standard_deviation_filtering": false
        },
        "fit": "Linear",
        "fn": 338,
        "include_baseline_error": false,
        "n": 340,
        "outlier_excluded": [
            180,
            111
        ],
        "reviewed": true,
        "user_excluded": [],
        "value": 10.312424147533335
    },
    "Ar38": {
        "error": 0.0059130535772544245,
        "error_type": "SEM",
        "filter_outliers_dict": {
            "filter_outliers": true,
            "iterations": 1,
            "std_devs": 3,
            "use_iqr_filtering": false,
            "use_standard_deviation_filtering": false
        },
        "fit": "Linear",
        "fn": 339,
        "include_baseline_error": false,
        "n": 340,
        "outlier_excluded": [
            150
        ],
        "reviewed": true,
        "user_excluded": [],
        "value": 0.982777187109124
    },
    "Ar39": {
        "error": 0.020663635578234744,
        "error_type": "SEM",
        "filter_outliers_dict": {
            "filter_outliers": true,
            "iterations": 1,
            "std_devs": 3,
            "use_iqr_filtering": false,
            "use_standard_deviation_filtering": false
        },
        "fit": "Parabolic",
        "fn": 337,
        "include_baseline_error": false,
        "n": 340,
        "outlier_excluded": [
            24,
            100,
            231
        ],
        "reviewed": true,
        "user_excluded": [],
        "value": 70.96315629563492
    },
    "Ar40": {
        "error": 0.051104879697049514,
        "error_type": "SEM",
        "filter_outliers_dict": {
            "filter_outliers": true,
            "iterations": 1,
            "std_devs": 3,
            "use_iqr_filtering": false,
            "use_standard_deviation_filtering": false
        },
        "fit": "Parabolic",
        "fn": 338,
        "include_baseline_error": false,
        "n": 340,
        "outlier_excluded": [
            250,
            5
        ],
        "reviewed": true,
        "user_excluded": [],
        "value": 360.0526837528589
    }
}