{
    "Ar36": {
        "error": 0.00027437067497623947,
        "error_type": "SEM",
        "filter_outliers_dict": {
            "filter_outliers": true,
            "iterations": 1,
            "std_devs": 2,
            "use_iqr_filtering": false,
            "use_standard_deviation_filtering": false
        },
        "fit": "Linear",
        "fn": 120,
        "include_baseline_error": false,
        "n": 120,
        "outlier_excluded": null,
        "reviewed": true,
        "user_excluded": null,
        "value": 0.011631327448205935
    },
    "Ar37": {
        "error": 0.01024495071324146,
        "error_type": "SEM",
        "filter_outliers_dict": {
            "filter_outliers": true,
            "iterations": 1,
            "std_devs": 2,
            "use_iqr_filtering": false,
            "use_standard_deviation_filtering": false
        },
        "fit": "Linear",
        "fn": 120,
        "include_baseline_error": false,
        "n": 120,
        "outlier_excluded": null,
        "reviewed": true,
        "user_excluded": null,
        "value": 0.042056761089296874
    },
    "Ar38": {
        "error": 0.004859641165366459,
        "error_type": "SEM",
        "filter_outliers_dict": {
            "filter_outliers": true,
            "iterations": 1,
            "std_devs": 2,
            "use_iqr_filtering": false,
            "use_standard_deviation_filtering": false
        },
        "fit": "Linear",
        "fn": 120,
        "include_baseline_error": false,
        "n": 120,
        "outlier_excluded": null,
        "reviewed": true,
        "user_excluded": null,
        "value": 0.46887683470964664
    },
    "Ar39": {
        "error": 0.014411791577093934,
        "error_type": "SEM",
        "filter_outliers_dict": {
            "filter_outliers": true,
            "iterations": 1,
            "std_devs": 2,
            "use_iqr_filtering": false,
            "use_standard_deviation_filtering": false
        },
        "fit": "Linear",
        "fn": 120,
        "include_baseline_error": false,
        "n": 120,
        "outlier_excluded": null,
        "reviewed": true,
        "user_excluded": null,
        "value": 32.635422115947
    },
    "Ar40": {
        "error": 0.03337293236975277,
        "error_type": "SEM",
        "filter_outliers_dict": {
            "filter_outliers": true,
            "iterations": 1,
            "std_devs": 2,
            "use_iqr_filtering": false,
            "use_standard_deviation_filtering": false
        },
        "fit": "Linear",
        "fn": 120,
        "include_baseline_error": false,
        "n": 120,
        "outlier_excluded": null,
        "reviewed": true,
        "user_excluded": null,
        "value": 400.74399898744366
    },
    "Ar41": {
        "error": 0.0017145540545792232,
        "error_type": "SEM",
        "filter_outliers_dict": {
            "filter_outliers": true,
            "iterations": 1,
            "std_devs": 2
        },
        "fit": "Average",
        "value": 0.020690936335460628
    }
}