{
    "AX": {
        "error": 0.0052891201924387034,
        "error_type": "SEM",
        "filter_outliers_dict": {
            "filter_outliers": true,
            "iterations": 1,
            "std_devs": 2,
            "use_iqr_filtering": false,
            "use_standard_deviation_filtering": false
        },
        "fit": "Average",
        "fn": 58,
        "include_baseline_error": false,
        "n": 60,
        "outlier_excluded": [
            45,
            22
        ],
        "reviewed": true,
        "user_excluded": [],
        "value": 0.07093055841838138
    },
    "H1": {
        "error": 0.008436123351788602,
        "error_type": "SEM",
        "filter_outliers_dict": {
            "filter_outliers": true,
            "iterations": 1,
            "std_devs": 2,
            "use_iqr_filtering": false,
            "use_standard_deviation_filtering": false
        },
        "fit": "Average",
        "fn": 58,
        "include_baseline_error": false,
        "n": 60,
        "outlier_excluded": [
            42,
            13
        ],
        "reviewed": true,
        "user_excluded": [],
        "value": 0.011083337801994338
    },
    "H2": {
        "error": 0.014623900765821634,
        "error_type": "SEM",
        "filter_outliers_dict": {
            "filter_outliers": true,
            "iterations": 1,
            "std_devs": 2,
            "use_iqr_filtering": false,
            "use_standard_deviation_filtering": false
        },
        "fit": "Average",
        "fn": 58,
        "include_baseline_error": false,
        "n": 60,
        "outlier_excluded": [
            33,
            50
        ],
        "reviewed": true,
        "user_excluded": [],
        "value": -0.019371180192984897
    },
    "L1": {
        "error": 0.01494198079251175,
        "error_type": "SEM",
        "filter_outliers_dict": {
            "filter_outliers": true,
            "iterations": 1,
            "std_devs": 2,
            "use_iqr_filtering": false,
            "use_standard_deviation_filtering": false
        },
        "fit": "Average",
        "fn": 55,
        "include_baseline_error": false,
        "n": 60,
        "outlier_excluded": [
            32,
            25,
            42,
            53,
            23
        ],
        "reviewed": true,
        "user_excluded": [],
        "value": 0.03890888114375147
    },
    "L2(CDD)": {
        "error": 0.0,
        "error_type": "SEM",
        "filter_outliers_dict": {
            "filter_outliers": true,
            "iterations": 1,
            "std_devs": 2
        },
        "fit": "average",
        "value": 0.0
    }
}