{
    "AX": {
        "error": 0.00019621213708698713,
        "fit": "Weighted Mean",
        "reference_data": {
            "es": [
                0.00022419978549602132,
                0.00020575180993398701,
                0.00022503660516039008,
                0.00020245329945015836,
                0.00021772656174318773,
                0.00021614709242712962,
                0.00021754913146359737,
                0.0001984856562130065,
                0.00019285217479599468,
                0.00022189180784670074,
                0.00020778957462114103,
                0.0002049655249115424,
                0.0002017865248007965,
                0.00021977789169899046,
                0.0002316576984270146,
                0.0002033754118484934,
                0.00020786354173140884,
                0.00020205937123756652,
                0.00021259411324780838,
                0.00021116578172210458,
                0.0002352201319843551,
                0.00020781853432074183,
                0.00020816103583358586,
                0.00020972115244941134,
                0.00020220564711103138,
                0.00020149500963948433,
                0.00021023552602184123,
                0.00023654198136981638,
                0.00020921709603760955,
                0.00020869733517063697,
                0.00020486556169473384,
                0.00021904494157573573,
                0.00019333731240353996,
                0.0002029804832135719
            ],
            "vs": [
                1.0005107458512863,
                1.000538401443859,
                1.000445348522601,
                1.0011917154729306,
                1.0009495790039187,
                1.0008790296673715,
                1.0011385188254194,
                1.0000798694458553,
                1.0000989052860452,
                1.0002462078046648,
                0.9991924533757431,
                0.9998852699210831,
                1.0002492774543246,
                1.0004916240389545,
                1.0002495405912901,
                1.0004203736284774,
                1.0004986459740621,
                1.000576716060277,
                1.0010697861673723,
                0.9999259847692957,
                0.9997217400670584,
                1.0000872818936246,
                0.999651486139878,
                0.999374939675569,
                0.9993855194739131,
                1.0002845925147832,
                1.0008581560334182,
                1.0006201027520685,
                1.0009284723772227,
                1.000722507617729,
                1.0004019446338352,
                1.0001655772516025,
                1.0004390694354899,
                1.0002906906929148
            ],
            "xs": [
                1560914360.0,
                1560920306.0,
                1560926298.0,
                1560932855.0,
                1560938839.0,
                1560945916.0,
                1560951393.0,
                1560962221.0,
                1560969709.0,
                1560977135.0,
                1560983542.0,
                1560989859.0,
                1560990892.0,
                1560993490.0,
                1560998004.0,
                1561002234.0,
                1561009217.0,
                1561019711.0,
                1561025738.0,
                1561046273.0,
                1561052205.0,
                1561059745.0,
                1561067205.0,
                1561074251.0,
                1561081754.0,
                1561089159.0,
                1561097232.0,
                1561104940.0,
                1561121501.0,
                1561130024.0,
                1561133886.0,
                1561138476.0,
                1561149740.0,
                1561152913.0
            ]
        },
        "reference_detector": "rad40",
        "references": [
            {
                "exclude": "ok",
                "record_id": "c-03-J-333",
                "uuid": "919a3ae2-84d8-4b20-a896-bae356641b19"
            },
            {
                "exclude": "ok",
                "record_id": "c-03-J-334",
                "uuid": "e5ce00d7-94e8-4a27-b189-f94a6ec29b1f"
            },
            {
                "exclude": "ok",
                "record_id": "c-03-J-335",
                "uuid": "5536b102-4819-4042-aa45-d48a10cfa821"
            },
            {
                "exclude": "ok",
                "record_id": "c-03-J-336",
                "uuid": "76b809a5-afc1-4fd2-a6bb-4a856dc6261d"
            },
            {
                "exclude": "ok",
                "record_id": "c-03-J-337",
                "uuid": "ce631f9b-9e4f-4e62-8bcc-426b1e3c6746"
            },
            {
                "exclude": "ok",
                "record_id": "c-03-J-338",
                "uuid": "cebfb385-0f2c-441a-a330-1b15cb299880"
            },
            {
                "exclude": "ok",
                "record_id": "c-03-J-339",
                "uuid": "50b26a53-09e2-469d-8fa1-1934485d4309"
            },
            {
                "exclude": "ok",
                "record_id": "c-03-J-340",
                "uuid": "4ff2f653-e684-4086-b14d-f12677e548c1"
            },
            {
                "exclude": "ok",
                "record_id": "c-03-J-341",
                "uuid": "e507f278-ecbe-42fc-8543-e070e6dae8fa"
            },
            {
                "exclude": "ok",
                "record_id": "c-03-J-342",
                "uuid": "08614d92-08e2-4982-844d-86781bbc841d"
            },
            {
                "exclude": "ok",
                "record_id": "c-03-J-343",
                "uuid": "795cb6f5-c7aa-42ca-bfc2-de8acb57c35e"
            },
            {
                "exclude": "ok",
                "record_id": "c-03-J-344",
                "uuid": "2586d33f-cc92-4872-bc81-5eb9129f81d0"
            },
            {
                "exclude": "ok",
                "record_id": "c-03-J-345",
                "uuid": "38bb0696-9bc1-4ef8-9bc3-d2e2b99d81df"
            },
            {
                "exclude": "ok",
                "record_id": "c-03-J-346",
                "uuid": "aa9bf18b-57dc-4402-8d3a-fb468b3d703a"
            },
            {
                "exclude": "ok",
                "record_id": "c-03-J-347",
                "uuid": "1da4c256-374f-45df-b2ce-07f6d16db4db"
            },
            {
                "exclude": "ok",
                "record_id": "c-03-J-348",
                "uuid": "988fa3d6-3c56-4dc8-8c1f-8d94d57e72cd"
            },
            {
                "exclude": "ok",
                "record_id": "c-03-J-349",
                "uuid": "242ae16b-703c-416d-a893-3d95b6e3e933"
            },
            {
                "exclude": "ok",
                "record_id": "c-03-J-350",
                "uuid": "4739608b-8aac-4d8a-9efd-49d69efce04e"
            },
            {
                "exclude": "ok",
                "record_id": "c-03-J-351",
                "uuid": "e61240a2-376b-4427-895f-a7db370b6f1a"
            },
            {
                "exclude": "ok",
                "record_id": "c-03-J-352",
                "uuid": "2f73b924-db29-450c-8f50-5302a0ca4a11"
            },
            {
                "exclude": "ok",
                "record_id": "c-03-J-353",
                "uuid": "19bbdf0e-802d-4f68-a18b-1e7e1f6afeff"
            },
            {
                "exclude": "ok",
                "record_id": "c-03-J-354",
                "uuid": "89fe1708-85ff-4f60-b916-e5730c7ec376"
            },
            {
                "exclude": "ok",
                "record_id": "c-03-J-355",
                "uuid": "81cdcf64-c0fc-478a-8e42-136905a03eca"
            },
            {
                "exclude": "ok",
                "record_id": "c-03-J-356",
                "uuid": "34fe2e2c-fd8a-45a1-a887-7a1a5f8c8443"
            },
            {
                "exclude": "ok",
                "record_id": "c-03-J-357",
                "uuid": "5697197d-b251-4879-b3c0-bf5a493f1669"
            },
            {
                "exclude": "ok",
                "record_id": "c-03-J-358",
                "uuid": "fe561b9a-a10d-47ee-a3fe-3bbcf345e330"
            },
            {
                "exclude": "ok",
                "record_id": "c-03-J-359",
                "uuid": "7f802ad4-73ee-4a5a-8b8c-6bd7563669b8"
            },
            {
                "exclude": "ok",
                "record_id": "c-03-J-360",
                "uuid": "9f49f5f3-6e07-4fd6-a472-426872163113"
            },
            {
                "exclude": "ok",
                "record_id": "c-03-J-361",
                "uuid": "c6ae3dfc-b21b-4242-a0df-f0eab21a2b20"
            },
            {
                "exclude": "ok",
                "record_id": "c-03-J-362",
                "uuid": "17c2b368-797b-4eaa-8044-7cd42f7518e9"
            },
            {
                "exclude": "ok",
                "record_id": "c-03-J-363",
                "uuid": "5890c177-4afb-4450-8f87-fa20b539add8"
            },
            {
                "exclude": "ok",
                "record_id": "c-03-J-364",
                "uuid": "3cc44618-d767-4a52-8c12-7c6096acd4a1"
            },
            {
                "exclude": "ok",
                "record_id": "c-03-J-365",
                "uuid": "2e569e68-43dc-4225-a1d2-6c6d509d3249"
            },
            {
                "exclude": "ok",
                "record_id": "c-03-J-366",
                "uuid": "455fb4ae-f404-40a7-9ce0-da63852f3417"
            }
        ],
        "reviewed": true,
        "standard_ratio": 6.600975,
        "value": 1.0001955147394164
    },
    "CDD": {
        "error": 0.0005320534644901159,
        "fit": "Weighted Mean",
        "reference_data": {
            "es": [
                0.0018056014185558157,
                0.0017987343677698443,
                0.001933961688914946,
                0.001881186425607468,
                0.0020072594918665084,
                0.0019214902682955933,
                0.0018496962122211374,
                0.0019770214657597917,
                0.0019828117289457645,
                0.001700400569000822,
                0.001816722705975685,
                0.002096083847918629,
                0.0019609616575130334,
                0.0020971247424877975,
                0.0018835150572240656,
                0.0019505391514931631,
                0.0019401432157691173,
                0.0018574943046299056,
                0.0018767851473115772,
                0.001810486400597275
            ],
            "vs": [
                1.008057222558928,
                1.0077150426076213,
                1.010180223137004,
                1.006207699182178,
                1.0073849866017166,
                1.0089608630787157,
                1.0068199285337076,
                1.0036077994575463,
                1.002084877295263,
                1.0015174446150705,
                1.0072673981265807,
                1.0044969864644495,
                1.0080663955109144,
                1.0106382784353527,
                1.007737345723166,
                1.0058311894312943,
                1.0073466327975773,
                1.0060113295852422,
                1.0056918837556683,
                1.0082271477680698
            ],
            "xs": [
                1560913427.0,
                1560927331.0,
                1560940307.0,
                1560955296.0,
                1560979384.0,
                1560990470.0,
                1560997581.0,
                1561005698.0,
                1561013634.0,
                1561024807.0,
                1561045341.0,
                1561064849.0,
                1561076863.0,
                1561090327.0,
                1561101904.0,
                1561106102.0,
                1561121063.0,
                1561135041.0,
                1561144617.0,
                1561154068.0
            ]
        },
        "reference_detector": "H1",
        "references": [
            {
                "exclude": "ok",
                "record_id": "a-02-J-1395",
                "uuid": "1a8496bc-48f0-40e5-a817-cb7b7ff203c8"
            },
            {
                "exclude": "ok",
                "record_id": "a-02-J-1396",
                "uuid": "b349ea71-79dd-41b0-8c69-cfd454ee4c2d"
            },
            {
                "exclude": "ok",
                "record_id": "a-02-J-1397",
                "uuid": "e8731835-605c-4a05-9bc9-08014f87635f"
            },
            {
                "exclude": "ok",
                "record_id": "a-02-J-1398",
                "uuid": "066d88f9-3615-4d10-a470-90f34d91a0c4"
            },
            {
                "exclude": "ok",
                "record_id": "a-02-J-1399",
                "uuid": "687f2161-c3f9-431a-bd78-7e1d09073596"
            },
            {
                "exclude": "ok",
                "record_id": "a-02-J-1400",
                "uuid": "c5cddba3-06cd-49c9-bec7-557b5a2b8113"
            },
            {
                "exclude": "ok",
                "record_id": "a-02-J-1401",
                "uuid": "9af6bbc3-ea92-470a-8061-b46ef59d7027"
            },
            {
                "exclude": "ok",
                "record_id": "a-02-J-1402",
                "uuid": "392e4fdb-7ef0-410f-a386-9e8c7edf148a"
            },
            {
                "exclude": "ok",
                "record_id": "a-02-J-1403",
                "uuid": "32a678bb-177f-4991-8c76-9e29eae4ca49"
            },
            {
                "exclude": "ok",
                "record_id": "a-02-J-1404",
                "uuid": "01536108-823a-45d0-8f17-3aa5939864b7"
            },
            {
                "exclude": "ok",
                "record_id": "a-02-J-1405",
                "uuid": "8c21fcd9-a33c-458c-bed5-e8f3c1eb094e"
            },
            {
                "exclude": "ok",
                "record_id": "a-02-J-1406",
                "uuid": "1c02cc1e-1ce0-4772-96e1-96067cd07a28"
            },
            {
                "exclude": "ok",
                "record_id": "a-02-J-1407",
                "uuid": "fd07c228-39a2-4613-8da5-216d6758c305"
            },
            {
                "exclude": "ok",
                "record_id": "a-02-J-1408",
                "uuid": "b9c12760-5ca5-4033-806d-201461044be4"
            },
            {
                "exclude": "ok",
                "record_id": "a-02-J-1409",
                "uuid": "e4952ba0-4461-4332-925c-06f01b1f15e5"
            },
            {
                "exclude": "ok",
                "record_id": "a-02-J-1410",
                "uuid": "3eba70af-cd23-490a-b0f6-f96d4e489e77"
            },
            {
                "exclude": "ok",
                "record_id": "a-02-J-1411",
                "uuid": "d1145ffd-8276-4e0f-8a81-43a7d342bd64"
            },
            {
                "exclude": "ok",
                "record_id": "a-02-J-1412",
                "uuid": "8d97f748-a1bc-49eb-868c-e27cac3677e3"
            },
            {
                "exclude": "ok",
                "record_id": "a-02-J-1413",
                "uuid": "1481c0b8-d192-4636-8025-b525c1923503"
            },
            {
                "exclude": "ok",
                "record_id": "a-02-J-1414",
                "uuid": "faed6c66-1ffb-4d26-98b6-9269acb4f764"
            }
        ],
        "reviewed": true,
        "standard_ratio": 295.5,
        "value": 1.0066492147984003
    },
    "H1": {
        "error": 1e-20,
        "fit": "default",
        "references": [],
        "value": 1.0
    },
    "H2": {
        "error": 1e-20,
        "fit": "default",
        "references": [],
        "value": 1.0
    },
    "L1": {
        "error": 1e-20,
        "fit": "default",
        "references": [],
        "value": 1.0
    },
    "L2": {
        "error": 1e-20,
        "fit": "default",
        "references": [],
        "value": 1.0
    }
}