{
    "Ar36": {
        "error": 0.0002339246911315702,
        "error_type": "SEM",
        "filter_outliers_dict": {
            "filter_outliers": true,
            "iterations": 1,
            "std_devs": 2
        },
        "fit": "Linear",
        "fn": 116,
        "include_baseline_error": false,
        "n": 120,
        "reviewed": true,
        "value": 0.0073918750192543915
    },
    "Ar37": {
        "error": 0.009710227973409797,
        "error_type": "SEM",
        "filter_outliers_dict": {
            "filter_outliers": true,
            "iterations": 1,
            "std_devs": 2
        },
        "fit": "Linear",
        "fn": 115,
        "include_baseline_error": false,
        "n": 120,
        "reviewed": true,
        "value": -0.23492030769787714
    },
    "Ar38": {
        "error": 0.00805398450479712,
        "error_type": "SEM",
        "filter_outliers_dict": {
            "filter_outliers": true,
            "iterations": 1,
            "std_devs": 2
        },
        "fit": "Linear",
        "fn": 115,
        "include_baseline_error": false,
        "n": 120,
        "reviewed": true,
        "value": 0.25355601385440873
    },
    "Ar39": {
        "error": 0.012915504504277944,
        "error_type": "SEM",
        "filter_outliers_dict": {
            "filter_outliers": true,
            "iterations": 1,
            "std_devs": 2
        },
        "fit": "Linear",
        "fn": 114,
        "include_baseline_error": false,
        "n": 120,
        "reviewed": true,
        "value": 25.483763116650017
    },
    "Ar40": {
        "error": 0.025785042201284462,
        "error_type": "SEM",
        "filter_outliers_dict": {
            "filter_outliers": true,
            "iterations": 1,
            "std_devs": 2
        },
        "fit": "Linear",
        "fn": 114,
        "include_baseline_error": false,
        "n": 120,
        "reviewed": true,
        "value": 239.2023678954189
    },
    "Ar41": {
        "error": 0.00442572988918781,
        "error_type": "SEM",
        "filter_outliers_dict": {
            "filter_outliers": true,
            "iterations": 1,
            "std_devs": 2
        },
        "fit": "Average",
        "value": -0.027319375479635064
    }
}